fs_server/__init__.py
fs_server/config.py
fs_server/serve.py
fs_server/serve_ftp.py
tendril_server_fs-0.2.9.dist-info/DESCRIPTION.rst
tendril_server_fs-0.2.9.dist-info/METADATA
tendril_server_fs-0.2.9.dist-info/RECORD
tendril_server_fs-0.2.9.dist-info/WHEEL
tendril_server_fs-0.2.9.dist-info/metadata.json
tendril_server_fs-0.2.9.dist-info/top_level.txt
