Metadata-Version: 2.0
Name: tendril-server-fs
Version: 0.2.9
Summary: XML-RPC Filesystem Server using Twisted and Pyfilesystems for Tendril
Home-page: https://github.com/chintal/tendril-fs-server
Author: Chintalagiri Shashank
Author-email: shashank@chintal.in
License: MIT
Keywords: tendril
Platform: UNKNOWN
Classifier: Development Status :: 4 - Beta
Classifier: License :: OSI Approved :: MIT License
Classifier: Natural Language :: English
Classifier: Programming Language :: Python
Requires-Dist: fs
Requires-Dist: twisted
